README.rst
setup.py
src/abi/__init__.py
src/abi.tools.uigenerator.egg-info/PKG-INFO
src/abi.tools.uigenerator.egg-info/SOURCES.txt
src/abi.tools.uigenerator.egg-info/dependency_links.txt
src/abi.tools.uigenerator.egg-info/entry_points.txt
src/abi.tools.uigenerator.egg-info/not-zip-safe
src/abi.tools.uigenerator.egg-info/requires.txt
src/abi.tools.uigenerator.egg-info/top_level.txt
src/abi/tools/__init__.py
src/abi/tools/generateuserinterface.py
src/abi/tools/ui/__init__.py
src/abi/tools/ui/ui2_uifileconverter.py
src/abi/tools/ui/ui_uifileconverter.py