Metadata-Version: 1.1
Name: abi.tools.uigenerator
Version: 0.1.0
Summary: Python client for generating Python user interface descriptions.
Home-page: https://github.com/ABI-Software/abi.tools.uigenerator
Author: Auckland Bioengineering Institute
Author-email: h.sorby@auckland.ac.nz
License: UNKNOWN
Keywords: abi user interface generator
Platform: UNKNOWN
Classifier: Development Status :: 3 - Alpha
Classifier: Topic :: Utilities
